ca.py
epicsMotor.py
epicsPV.py
CaChannel/CaChannel.py
CaChannel/__init__.py
CaChannel/_ca.cpython-38-x86_64-linux-gnu.so
CaChannel/_version.py
CaChannel/ca.py
CaChannel/util.py
CaChannel-3.2.0.dist-info/LICENSE
CaChannel-3.2.0.dist-info/METADATA
CaChannel-3.2.0.dist-info/WHEEL
CaChannel-3.2.0.dist-info/top_level.txt
CaChannel-3.2.0.dist-info/RECORD
