Metadata-Version: 2.1
Name: CaChannel
Version: 3.2.0
Summary: CaChannel Interface to EPICS
Home-page: http://pypi.python.org/pypi/cachannel
Author: Xiaoqiang Wang
Author-email: xiaoqiang.wang@psi.ch
License: BSD
Platform: Windows
Platform: Linux
Platform: Mac OS X
Classifier: Development Status :: 5 - Production/Stable
Classifier: Environment :: Console
Classifier: Intended Audience :: Developers
Classifier: Programming Language :: C
Classifier: Programming Language :: Python :: 2
Classifier: Programming Language :: Python :: 2.6
Classifier: Programming Language :: Python :: 2.7
Classifier: Programming Language :: Python :: 3
Classifier: License :: OSI Approved :: BSD License
Classifier: Topic :: Scientific/Engineering
License-File: LICENSE
